.coveragerc
.gitignore
.travis.yml
CHANGES.txt
CONTRIBUTORS.txt
MANIFEST.in
README.rst
bootstrap-buildout.py
bootstrap.py
bootstrap4.py
bootstrap5.py
buildout.cfg
setup.py
test-4.1.x.cfg
test-4.2.x.cfg
test-4.3.x.cfg
test-5.0.x.cfg
test-5.1.x.cfg
Products/__init__.py
Products.AutoUserMakerPASPlugin.egg-info/PKG-INFO
Products.AutoUserMakerPASPlugin.egg-info/SOURCES.txt
Products.AutoUserMakerPASPlugin.egg-info/dependency_links.txt
Products.AutoUserMakerPASPlugin.egg-info/entry_points.txt
Products.AutoUserMakerPASPlugin.egg-info/namespace_packages.txt
Products.AutoUserMakerPASPlugin.egg-info/not-zip-safe
Products.AutoUserMakerPASPlugin.egg-info/requires.txt
Products.AutoUserMakerPASPlugin.egg-info/top_level.txt
Products/AutoUserMakerPASPlugin/README.rst
Products/AutoUserMakerPASPlugin/__init__.py
Products/AutoUserMakerPASPlugin/add-AutoUserMakerPASPlugin.zpt
Products/AutoUserMakerPASPlugin/auth.py
Products/AutoUserMakerPASPlugin/autousermaker.gif
Products/AutoUserMakerPASPlugin/config.zpt
Products/AutoUserMakerPASPlugin/configure.zcml
Products/AutoUserMakerPASPlugin/i18n.sh
Products/AutoUserMakerPASPlugin/rolemap.zpt
Products/AutoUserMakerPASPlugin/zmi.py
Products/AutoUserMakerPASPlugin/Extensions/Install.py
Products/AutoUserMakerPASPlugin/Extensions/__init__.py
Products/AutoUserMakerPASPlugin/apache/Rewrite.py
Products/AutoUserMakerPASPlugin/docs/LICENSE.GPL
Products/AutoUserMakerPASPlugin/docs/LICENSE.txt
Products/AutoUserMakerPASPlugin/locales/AutoUserMakerPASPlugin.pot
Products/AutoUserMakerPASPlugin/locales/de/LC_MESSAGES/AutoUserMakerPASPlugin.po
Products/AutoUserMakerPASPlugin/locales/en/LC_MESSAGES/AutoUserMakerPASPlugin.po
Products/AutoUserMakerPASPlugin/tests/AutoUserMakerPASPlugin.txt
Products/AutoUserMakerPASPlugin/tests/TestBrowers.txt
Products/AutoUserMakerPASPlugin/tests/__init__.py
Products/AutoUserMakerPASPlugin/tests/base.py
Products/AutoUserMakerPASPlugin/tests/test_doctests.py
Products/AutoUserMakerPASPlugin/tests/test_plugin.py
Products/AutoUserMakerPASPlugin/tests/utils.py