Metadata-Version: 1.1
Name: Products.AutoUserMakerPASPlugin
Version: 2.1.1
Summary: Automatically create PAS users when authentication in Plone
Home-page: http://pypi.python.org/pypi/Products.AutoUserMakerPASPlugin/
Author: Tom Gross
Author-email: itconsense@gmail.com
License: GPL
Keywords: plone authentication shibboleth pas security
Platform: UNKNOWN
Classifier: Framework :: Zope2
Classifier: Framework :: Plone
Classifier: Framework :: Plone :: 4.1
Classifier: Framework :: Plone :: 4.2
Classifier: Framework :: Plone :: 4.3
Classifier: Framework :: Plone :: 5.0
Classifier: Framework :: Plone :: 5.1
Classifier: Programming Language :: Python
Classifier: Programming Language :: Python :: 2.6
Classifier: Programming Language :: Python :: 2.7
